README
setup.py
src/SpiffSignal/Slot.py
src/SpiffSignal/Trackable.py
src/SpiffSignal/__init__.py
src/SpiffSignal.egg-info/PKG-INFO
src/SpiffSignal.egg-info/SOURCES.txt
src/SpiffSignal.egg-info/dependency_links.txt
src/SpiffSignal.egg-info/top_level.txt