Metadata-Version: 1.0
Name: SpiffSignal
Version: 0.1.0
Summary: A signal/event mechanism for Python
Home-page: http://code.google.com/p/spiff-signal/
Author: Samuel Abels
Author-email: cheeseshop.python.org@debain.org
License: lGPLv2
Keywords: spiff signal event mechanism slot trackable
Platform: UNKNOWN
Classifier: Development Status :: 5 - Production/Stable
Classifier: Intended Audience :: Developers
Classifier: License :: OSI Approved :: GNU Library or Lesser General Public License (LGPL)
Classifier: Programming Language :: Python
Classifier: Topic :: Other/Nonlisted Topic
Classifier: Topic :: Software Development :: Libraries
Classifier: Topic :: Software Development :: Libraries :: Python Modules
